[
    {
        "inputs": [
            {
                "internalType": "string",
                "name": "_name",
                "type": "string"
            },
            {
                "internalType": "string",
                "name": "_symbol",
                "type": "string"
            },
            {
                "internalType": "uint256",
                "name": "_decimals",
                "type": "uint256"
            },
            {
                "internalType": "address",
                "name": "_controller",
                "type": "address"
            },
            {
                "internalType": "address",
                "name": "_underlying",
                "type": "address"
            },
            {
                "internalType": "address",
                "name": "_interestModule",
                "type": "address"
            }
        ],
        "stateMutability": "nonpayable",
        "type": "constructor"
    },
    {
        "anonymous": false,
        "inputs": [
            {
                "indexed": true,
                "internalType": "address",
                "name": "owner",
                "type": "address"
            },
            {
                "indexed": true,
                "internalType": "address",
                "name": "spender",
                "type": "address"
            },
            {
                "indexed": false,
                "internalType": "uint256",
                "name": "amount",
                "type": "uint256"
            }
        ],
        "name": "Approval",
        "type": "event"
    },
    {
        "anonymous": false,
        "inputs": [
            {
                "indexed": false,
                "internalType": "address",
                "name": "user",
                "type": "address"
            },
            {
                "indexed": false,
                "internalType": "uint256",
                "name": "amount",
                "type": "uint256"
            },
            {
                "indexed": false,
                "internalType": "address",
                "name": "vToken",
                "type": "address"
            }
        ],
        "name": "CloseLoan",
        "type": "event"
    },
    {
        "anonymous": false,
        "inputs": [
            {
                "indexed": false,
                "internalType": "address",
                "name": "user",
                "type": "address"
            },
            {
                "indexed": false,
                "internalType": "uint256",
                "name": "amount",
                "type": "uint256"
            },
            {
                "indexed": false,
                "internalType": "address",
                "name": "vToken",
                "type": "address"
            }
        ],
        "name": "Deposit",
        "type": "event"
    },
    {
        "anonymous": false,
        "inputs": [
            {
                "indexed": false,
                "internalType": "address",
                "name": "user",
                "type": "address"
            },
            {
                "indexed": false,
                "internalType": "uint256",
                "name": "amount",
                "type": "uint256"
            },
            {
                "indexed": false,
                "internalType": "address",
                "name": "vToken",
                "type": "address"
            }
        ],
        "name": "NewBorrow",
        "type": "event"
    },
    {
        "anonymous": false,
        "inputs": [
            {
                "indexed": true,
                "internalType": "address",
                "name": "from",
                "type": "address"
            },
            {
                "indexed": true,
                "internalType": "address",
                "name": "to",
                "type": "address"
            },
            {
                "indexed": false,
                "internalType": "uint256",
                "name": "amount",
                "type": "uint256"
            }
        ],
        "name": "Transfer",
        "type": "event"
    },
    {
        "anonymous": false,
        "inputs": [
            {
                "indexed": false,
                "internalType": "address",
                "name": "user",
                "type": "address"
            },
            {
                "indexed": false,
                "internalType": "uint256",
                "name": "amount",
                "type": "uint256"
            },
            {
                "indexed": false,
                "internalType": "address",
                "name": "vToken",
                "type": "address"
            }
        ],
        "name": "Withdraw",
        "type": "event"
    },
    {
        "anonymous": false,
        "inputs": [
            {
                "indexed": false,
                "internalType": "address",
                "name": "oldAdmin",
                "type": "address"
            },
            {
                "indexed": false,
                "internalType": "address",
                "name": "newAdmin",
                "type": "address"
            }
        ],
        "name": "newAdmin",
        "type": "event"
    },
    {
        "anonymous": false,
        "inputs": [
            {
                "indexed": false,
                "internalType": "contract PaladinControllerInterface",
                "name": "oldController",
                "type": "address"
            },
            {
                "indexed": false,
                "internalType": "contract PaladinControllerInterface",
                "name": "newController",
                "type": "address"
            }
        ],
        "name": "newController",
        "type": "event"
    },
    {
        "inputs": [],
        "name": "accrualBlockNumber",
        "outputs": [
            {
                "internalType": "uint256",
                "name": "",
                "type": "uint256"
            }
        ],
        "stateMutability": "view",
        "type": "function"
    },
    {
        "inputs": [
            {
                "internalType": "address",
                "name": "owner",
                "type": "address"
            },
            {
                "internalType": "address",
                "name": "spender",
                "type": "address"
            }
        ],
        "name": "allowance",
        "outputs": [
            {
                "internalType": "uint256",
                "name": "",
                "type": "uint256"
            }
        ],
        "stateMutability": "view",
        "type": "function"
    },
    {
        "inputs": [
            {
                "internalType": "address",
                "name": "spender",
                "type": "address"
            },
            {
                "internalType": "uint256",
                "name": "amount",
                "type": "uint256"
            }
        ],
        "name": "approve",
        "outputs": [
            {
                "internalType": "bool",
                "name": "",
                "type": "bool"
            }
        ],
        "stateMutability": "nonpayable",
        "type": "function"
    },
    {
        "inputs": [
            {
                "internalType": "address",
                "name": "owner",
                "type": "address"
            }
        ],
        "name": "balanceOf",
        "outputs": [
            {
                "internalType": "uint256",
                "name": "",
                "type": "uint256"
            }
        ],
        "stateMutability": "view",
        "type": "function"
    },
    {
        "inputs": [],
        "name": "borrowIndex",
        "outputs": [
            {
                "internalType": "uint256",
                "name": "",
                "type": "uint256"
            }
        ],
        "stateMutability": "view",
        "type": "function"
    },
    {
        "inputs": [],
        "name": "controller",
        "outputs": [
            {
                "internalType": "contract PaladinControllerInterface",
                "name": "",
                "type": "address"
            }
        ],
        "stateMutability": "view",
        "type": "function"
    },
    {
        "inputs": [],
        "name": "decimals",
        "outputs": [
            {
                "internalType": "uint256",
                "name": "",
                "type": "uint256"
            }
        ],
        "stateMutability": "view",
        "type": "function"
    },
    {
        "inputs": [],
        "name": "name",
        "outputs": [
            {
                "internalType": "string",
                "name": "",
                "type": "string"
            }
        ],
        "stateMutability": "view",
        "type": "function"
    },
    {
        "inputs": [],
        "name": "reserveFactor",
        "outputs": [
            {
                "internalType": "uint256",
                "name": "",
                "type": "uint256"
            }
        ],
        "stateMutability": "view",
        "type": "function"
    },
    {
        "inputs": [],
        "name": "symbol",
        "outputs": [
            {
                "internalType": "string",
                "name": "",
                "type": "string"
            }
        ],
        "stateMutability": "view",
        "type": "function"
    },
    {
        "inputs": [],
        "name": "totalBorrowed",
        "outputs": [
            {
                "internalType": "uint256",
                "name": "",
                "type": "uint256"
            }
        ],
        "stateMutability": "view",
        "type": "function"
    },
    {
        "inputs": [],
        "name": "totalReserve",
        "outputs": [
            {
                "internalType": "uint256",
                "name": "",
                "type": "uint256"
            }
        ],
        "stateMutability": "view",
        "type": "function"
    },
    {
        "inputs": [],
        "name": "totalSupply",
        "outputs": [
            {
                "internalType": "uint256",
                "name": "",
                "type": "uint256"
            }
        ],
        "stateMutability": "view",
        "type": "function"
    },
    {
        "inputs": [
            {
                "internalType": "address",
                "name": "dest",
                "type": "address"
            },
            {
                "internalType": "uint256",
                "name": "amount",
                "type": "uint256"
            }
        ],
        "name": "transfer",
        "outputs": [
            {
                "internalType": "bool",
                "name": "",
                "type": "bool"
            }
        ],
        "stateMutability": "nonpayable",
        "type": "function"
    },
    {
        "inputs": [
            {
                "internalType": "address",
                "name": "dest",
                "type": "address"
            },
            {
                "internalType": "address",
                "name": "src",
                "type": "address"
            },
            {
                "internalType": "uint256",
                "name": "amount",
                "type": "uint256"
            }
        ],
        "name": "transferFrom",
        "outputs": [
            {
                "internalType": "bool",
                "name": "",
                "type": "bool"
            }
        ],
        "stateMutability": "nonpayable",
        "type": "function"
    },
    {
        "inputs": [],
        "name": "underlying",
        "outputs": [
            {
                "internalType": "contract IERC20",
                "name": "",
                "type": "address"
            }
        ],
        "stateMutability": "view",
        "type": "function"
    },
    {
        "inputs": [],
        "name": "_underlyingBalance",
        "outputs": [
            {
                "internalType": "uint256",
                "name": "",
                "type": "uint256"
            }
        ],
        "stateMutability": "view",
        "type": "function"
    },
    {
        "inputs": [
            {
                "internalType": "uint256",
                "name": "amount",
                "type": "uint256"
            }
        ],
        "name": "deposit",
        "outputs": [
            {
                "internalType": "uint256",
                "name": "",
                "type": "uint256"
            }
        ],
        "stateMutability": "nonpayable",
        "type": "function"
    },
    {
        "inputs": [
            {
                "internalType": "uint256",
                "name": "amount",
                "type": "uint256"
            }
        ],
        "name": "withdraw",
        "outputs": [
            {
                "internalType": "uint256",
                "name": "",
                "type": "uint256"
            }
        ],
        "stateMutability": "nonpayable",
        "type": "function"
    },
    {
        "inputs": [
            {
                "internalType": "uint256",
                "name": "amount",
                "type": "uint256"
            },
            {
                "internalType": "uint256",
                "name": "feeAmount",
                "type": "uint256"
            }
        ],
        "name": "borrow",
        "outputs": [
            {
                "internalType": "uint256",
                "name": "",
                "type": "uint256"
            }
        ],
        "stateMutability": "nonpayable",
        "type": "function"
    },
    {
        "inputs": [
            {
                "internalType": "address",
                "name": "loanPool",
                "type": "address"
            },
            {
                "internalType": "uint256",
                "name": "feeAmount",
                "type": "uint256"
            }
        ],
        "name": "expandBorrow",
        "outputs": [
            {
                "internalType": "uint256",
                "name": "",
                "type": "uint256"
            }
        ],
        "stateMutability": "nonpayable",
        "type": "function"
    },
    {
        "inputs": [
            {
                "internalType": "address",
                "name": "loanPool",
                "type": "address"
            }
        ],
        "name": "killBorrow",
        "outputs": [
            {
                "internalType": "uint256",
                "name": "",
                "type": "uint256"
            }
        ],
        "stateMutability": "nonpayable",
        "type": "function"
    },
    {
        "inputs": [
            {
                "internalType": "address",
                "name": "loanPool",
                "type": "address"
            }
        ],
        "name": "closeBorrow",
        "outputs": [
            {
                "internalType": "uint256",
                "name": "",
                "type": "uint256"
            }
        ],
        "stateMutability": "nonpayable",
        "type": "function"
    },
    {
        "inputs": [],
        "name": "getLoansPools",
        "outputs": [
            {
                "internalType": "address[]",
                "name": "",
                "type": "address[]"
            }
        ],
        "stateMutability": "view",
        "type": "function"
    },
    {
        "inputs": [
            {
                "internalType": "address",
                "name": "borrower",
                "type": "address"
            }
        ],
        "name": "getLoansByBorrowerStored",
        "outputs": [
            {
                "internalType": "address[]",
                "name": "",
                "type": "address[]"
            }
        ],
        "stateMutability": "view",
        "type": "function"
    },
    {
        "inputs": [
            {
                "internalType": "address",
                "name": "borrower",
                "type": "address"
            }
        ],
        "name": "getLoansByBorrower",
        "outputs": [
            {
                "internalType": "address[]",
                "name": "",
                "type": "address[]"
            }
        ],
        "stateMutability": "nonpayable",
        "type": "function"
    },
    {
        "inputs": [
            {
                "internalType": "address",
                "name": "__loanPool",
                "type": "address"
            }
        ],
        "name": "getBorrowDataStored",
        "outputs": [
            {
                "internalType": "address",
                "name": "_borrower",
                "type": "address"
            },
            {
                "internalType": "address",
                "name": "_loanPool",
                "type": "address"
            },
            {
                "internalType": "uint256",
                "name": "_amount",
                "type": "uint256"
            },
            {
                "internalType": "address",
                "name": "_underlying",
                "type": "address"
            },
            {
                "internalType": "uint256",
                "name": "_feesAmount",
                "type": "uint256"
            },
            {
                "internalType": "uint256",
                "name": "_feesUsed",
                "type": "uint256"
            },
            {
                "internalType": "bool",
                "name": "_closed",
                "type": "bool"
            }
        ],
        "stateMutability": "view",
        "type": "function"
    },
    {
        "inputs": [
            {
                "internalType": "address",
                "name": "__loanPool",
                "type": "address"
            }
        ],
        "name": "getBorrowData",
        "outputs": [
            {
                "internalType": "address",
                "name": "_borrower",
                "type": "address"
            },
            {
                "internalType": "address",
                "name": "_loanPool",
                "type": "address"
            },
            {
                "internalType": "uint256",
                "name": "_amount",
                "type": "uint256"
            },
            {
                "internalType": "address",
                "name": "_underlying",
                "type": "address"
            },
            {
                "internalType": "uint256",
                "name": "_feesAmount",
                "type": "uint256"
            },
            {
                "internalType": "uint256",
                "name": "_feesUsed",
                "type": "uint256"
            },
            {
                "internalType": "bool",
                "name": "_closed",
                "type": "bool"
            }
        ],
        "stateMutability": "nonpayable",
        "type": "function"
    },
    {
        "inputs": [],
        "name": "borrowRatePerBlock",
        "outputs": [
            {
                "internalType": "uint256",
                "name": "",
                "type": "uint256"
            }
        ],
        "stateMutability": "view",
        "type": "function"
    },
    {
        "inputs": [],
        "name": "supplyRatePerBlock",
        "outputs": [
            {
                "internalType": "uint256",
                "name": "",
                "type": "uint256"
            }
        ],
        "stateMutability": "view",
        "type": "function"
    },
    {
        "inputs": [],
        "name": "totalBorrowsCurrent",
        "outputs": [
            {
                "internalType": "uint256",
                "name": "",
                "type": "uint256"
            }
        ],
        "stateMutability": "nonpayable",
        "type": "function"
    },
    {
        "inputs": [],
        "name": "exchangeRateCurrent",
        "outputs": [
            {
                "internalType": "uint256",
                "name": "",
                "type": "uint256"
            }
        ],
        "stateMutability": "nonpayable",
        "type": "function"
    },
    {
        "inputs": [],
        "name": "exchangeRateStored",
        "outputs": [
            {
                "internalType": "uint256",
                "name": "",
                "type": "uint256"
            }
        ],
        "stateMutability": "view",
        "type": "function"
    },
    {
        "inputs": [],
        "name": "_updateInterest",
        "outputs": [
            {
                "internalType": "bool",
                "name": "",
                "type": "bool"
            }
        ],
        "stateMutability": "nonpayable",
        "type": "function"
    },
    {
        "inputs": [
            {
                "internalType": "address payable",
                "name": "_newAdmin",
                "type": "address"
            }
        ],
        "name": "setNewAdmin",
        "outputs": [],
        "stateMutability": "nonpayable",
        "type": "function"
    },
    {
        "inputs": [
            {
                "internalType": "address",
                "name": "_newController",
                "type": "address"
            }
        ],
        "name": "setNewController",
        "outputs": [],
        "stateMutability": "nonpayable",
        "type": "function"
    },
    {
        "inputs": [
            {
                "internalType": "address",
                "name": "_interestModule",
                "type": "address"
            }
        ],
        "name": "setNewInterestModule",
        "outputs": [],
        "stateMutability": "nonpayable",
        "type": "function"
    },
    {
        "inputs": [
            {
                "internalType": "uint256",
                "name": "_amount",
                "type": "uint256"
            }
        ],
        "name": "addReserve",
        "outputs": [],
        "stateMutability": "nonpayable",
        "type": "function"
    },
    {
        "inputs": [
            {
                "internalType": "uint256",
                "name": "_amount",
                "type": "uint256"
            }
        ],
        "name": "removeReserve",
        "outputs": [],
        "stateMutability": "nonpayable",
        "type": "function"
    }
]